dnikit/__init__.py
dnikit/_availability.py
dnikit/_dict_utils.py
dnikit/_logging.py
dnikit/py.typed
dnikit/base/__init__.py
dnikit/base/_cached_producer.py
dnikit/base/_image_producer.py
dnikit/base/_introspector.py
dnikit/base/_model.py
dnikit/base/_multi_introspect.py
dnikit/base/_pipeline.py
dnikit/base/_producer.py
dnikit/base/_response_info.py
dnikit/base/_traintest_producer.py
dnikit/base/_batch/__init__.py
dnikit/base/_batch/_batch.py
dnikit/base/_batch/_fields.py
dnikit/base/_batch/_metadata_storage.py
dnikit/base/_batch/_storage.py
dnikit/exceptions/__init__.py
dnikit/exceptions/_dnikit_exceptions.py
dnikit/introspectors/__init__.py
dnikit/introspectors/_duplicates.py
dnikit/introspectors/_dim_reduction/__init__.py
dnikit/introspectors/_dim_reduction/_dimension_reduction.py
dnikit/introspectors/_dim_reduction/_protocols.py
dnikit/introspectors/_dim_reduction/_reducers.py
dnikit/introspectors/_familiarity/__init__.py
dnikit/introspectors/_familiarity/_familiarity.py
dnikit/introspectors/_familiarity/_gaussian_familiarity.py
dnikit/introspectors/_familiarity/_gmm_familiarity.py
dnikit/introspectors/_familiarity/_protocols.py
dnikit/introspectors/_iua/__init__.py
dnikit/introspectors/_iua/_iua.py
dnikit/introspectors/_pfa/__init__.py
dnikit/introspectors/_pfa/_covariances_calculator.py
dnikit/introspectors/_pfa/_pfa.py
dnikit/introspectors/_pfa/_pfa_algorithms.py
dnikit/introspectors/_pfa/_pfa_units.py
dnikit/introspectors/_pfa/_recommendation.py
dnikit/introspectors/_report/__init__.py
dnikit/introspectors/_report/_dataframe_formatting.py
dnikit/introspectors/_report/_dataset_report.py
dnikit/introspectors/_report/_dataset_report_stages.py
dnikit/introspectors/_report/_familiarity_wrappers.py
dnikit/introspectors/_report/_report_builder_introspectors.py
dnikit/introspectors/_report/_string_util.py
dnikit/processors/__init__.py
dnikit/processors/_base_processor.py
dnikit/processors/_image_processors.py
dnikit/processors/_metadata_processors.py
dnikit-2.0.0.dist-info/WHEEL
dnikit-2.0.0.dist-info/METADATA
dnikit-2.0.0.dist-info/RECORD
